equilib/__init__.py
equilib/info.py
equilib/cube2equi/__init__.py
equilib/cube2equi/base.py
equilib/cube2equi/numpy.py
equilib/cube2equi/torch.py
equilib/equi2cube/__init__.py
equilib/equi2cube/base.py
equilib/equi2cube/numpy.py
equilib/equi2cube/torch.py
equilib/equi2equi/__init__.py
equilib/equi2equi/base.py
equilib/equi2equi/numpy.py
equilib/equi2equi/torch.py
equilib/equi2pers/__init__.py
equilib/equi2pers/base.py
equilib/equi2pers/numpy.py
equilib/equi2pers/torch.py
equilib/grid_sample/__init__.py
equilib/grid_sample/cpp/__init__.py
equilib/grid_sample/cpp/setup.py
equilib/grid_sample/numpy/__init__.py
equilib/grid_sample/numpy/bicubic.py
equilib/grid_sample/numpy/bilinear.py
equilib/grid_sample/numpy/grid_sample.py
equilib/grid_sample/numpy/nearest.py
equilib/grid_sample/torch/__init__.py
equilib/grid_sample/torch/bicubic.py
equilib/grid_sample/torch/bilinear.py
equilib/grid_sample/torch/grid_sample.py
equilib/grid_sample/torch/native.py
equilib/grid_sample/torch/nearest.py
equilib/numpy_utils/__init__.py
equilib/numpy_utils/grid.py
equilib/numpy_utils/intrinsic.py
equilib/numpy_utils/rotation.py
equilib/torch_utils/__init__.py
equilib/torch_utils/func.py
equilib/torch_utils/grid.py
equilib/torch_utils/intrinsic.py
equilib/torch_utils/rotation.py
tests/cube2equi/__init__.py
tests/cube2equi/numpy_run_baselines.py
tests/cube2equi/torch_run.py
tests/equi2cube/__init__.py
tests/equi2cube/numpy_run_baselines.py
tests/equi2cube/torch_run.py
tests/equi2equi/__init__.py
tests/equi2equi/numpy_run_baselines.py
tests/equi2equi/torch_run.py
tests/equi2pers/__init__.py
tests/equi2pers/numpy_convert_grid.py
tests/equi2pers/numpy_inv.py
tests/equi2pers/numpy_matmul.py
tests/equi2pers/numpy_prep.py
tests/equi2pers/numpy_run_baselines.py
tests/equi2pers/torch_run.py
tests/grid_sample/__init__.py
tests/grid_sample/helpers.py
tests/grid_sample/numpy/__init__.py
tests/grid_sample/numpy/baselines.py
tests/grid_sample/numpy/bicubic.py
tests/grid_sample/numpy/bilinear.py
pyequilib-0.5.8.dist-info/LICENSE
pyequilib-0.5.8.dist-info/METADATA
pyequilib-0.5.8.dist-info/WHEEL
pyequilib-0.5.8.dist-info/top_level.txt
pyequilib-0.5.8.dist-info/RECORD
