Metadata-Version: 2.1
Name: pyequilib
Version: 0.5.8
Summary: equirectangular image processing with python using minimum dependencies
Home-page: https://github.com/haruishi43/equilib
Author: Haruya Ishikawa
Author-email: haru.ishi43@gmail.com
License: Apache License 2.0
Keywords: Equirectangular,Computer Vision
Classifier: Development Status :: 5 - Production/Stable
Classifier: Intended Audience :: Developers
Classifier: Natural Language :: English
Classifier: Programming Language :: Python
Classifier: Programming Language :: Python :: 3.8
Classifier: Programming Language :: Python :: 3.9
Classifier: Programming Language :: Python :: 3.10
Requires-Python: >=3.6
License-File: LICENSE
Requires-Dist: numpy
